cellmqtt/__init__.py
cellmqtt/cellmqtt.py
cellmqtt-0.1.0.dist-info/LICENSE
cellmqtt-0.1.0.dist-info/METADATA
cellmqtt-0.1.0.dist-info/WHEEL
cellmqtt-0.1.0.dist-info/top_level.txt
cellmqtt-0.1.0.dist-info/RECORD
