Metadata-Version: 2.1
Name: cellmqtt
Version: 0.1.0
Summary: Lightweight IoT MQTT library for mobile network chips.
Home-page: https://github.com/lioreshai/cellmqtt
Author: Liore Shai
Project-URL: Documentation, https://github.com/lioreshai/cellmqtt
Project-URL: Bug Reports, https://github.com/lioreshai/cellmqtt/issues
Project-URL: Source Code, https://github.com/lioreshai/cellmqtt
Keywords: MQTT,iot,cellular,gsm,gprs,sim800c
Classifier: Development Status :: 3 - Alpha
Classifier: Intended Audience :: Developers
Classifier: Programming Language :: Python :: 3.7
Classifier: Programming Language :: Python :: 3.8
Classifier: Programming Language :: Python :: 3.9
Classifier: Programming Language :: Python :: 3 :: Only
Classifier: License :: OSI Approved :: MIT License
Classifier: Operating System :: OS Independent
Requires-Python: >=3.7
License-File: LICENSE
Provides-Extra: dev
Requires-Dist: check-manifest ; extra == 'dev'
